snapshottest/__init__.py
snapshottest/diff.py
snapshottest/django.py
snapshottest/error.py
snapshottest/file.py
snapshottest/formatter.py
snapshottest/formatters.py
snapshottest/generic_repr.py
snapshottest/module.py
snapshottest/nose.py
snapshottest/pytest.py
snapshottest/reporting.py
snapshottest/snapshot.py
snapshottest/sorted_dict.py
snapshottest/unittest.py
snapshottest_patch-1.0.0.dist-info/LICENSE
snapshottest_patch-1.0.0.dist-info/METADATA
snapshottest_patch-1.0.0.dist-info/WHEEL
snapshottest_patch-1.0.0.dist-info/entry_points.txt
snapshottest_patch-1.0.0.dist-info/top_level.txt
snapshottest_patch-1.0.0.dist-info/RECORD
