Metadata-Version: 2.1
Name: snapshottest-patch
Version: 1.0.0
Summary: Snapshot testing for pytest, unittest, Django, and Nose
Home-page: https://github.com/syrusakbary/snapshottest
Author: Syrus Akbary
Author-email: me@syrusakbary.com
License: MIT
Classifier: Development Status :: 5 - Production/Stable
Classifier: Framework :: Django
Classifier: Framework :: Pytest
Classifier: Intended Audience :: Developers
Classifier: Operating System :: OS Independent
Classifier: Topic :: Software Development :: Libraries
Classifier: Topic :: Software Development :: Testing
Classifier: Topic :: Software Development :: Testing :: Unit
License-File: LICENSE
Requires-Dist: termcolor
Requires-Dist: fastdiff <1,>=0.1.4
Provides-Extra: nose
Requires-Dist: nose ; extra == 'nose'
Provides-Extra: pytest
Requires-Dist: pytest ; extra == 'pytest'
Provides-Extra: test
Requires-Dist: pytest >=4.6 ; extra == 'test'
Requires-Dist: pytest-cov ; extra == 'test'
Requires-Dist: nose ; extra == 'test'
Requires-Dist: django >=1.10.6 ; extra == 'test'
